uberegg.py
uberegg-0.1.1.dist-info/LICENSE
uberegg-0.1.1.dist-info/METADATA
uberegg-0.1.1.dist-info/WHEEL
uberegg-0.1.1.dist-info/entry_points.txt
uberegg-0.1.1.dist-info/top_level.txt
uberegg-0.1.1.dist-info/RECORD
