Metadata-Version: 2.1
Name: uberegg
Version: 0.1.1
Summary: Uber-egg (egg with dependencies) builder
Home-page: https://github.com/divtiply/uberegg
Author: divtiply
License: MIT
Platform: UNKNOWN
Classifier: License :: OSI Approved :: MIT License
Classifier: Programming Language :: Python :: 3
License-File: LICENSE
